cli/__init__.py
cli/main.py
core/__init__.py
core/analysis.py
core/blamer.py
core/history.py
core/insight.py
core/patch_engine.py
core/reporter.py
core/summarizer.py
core/visualizer.py
patchmind-0.1.5.dist-info/licenses/LICENSE
patchmind-0.1.5.dist-info/METADATA
patchmind-0.1.5.dist-info/WHEEL
patchmind-0.1.5.dist-info/entry_points.txt
patchmind-0.1.5.dist-info/top_level.txt
patchmind-0.1.5.dist-info/RECORD
