Metadata-Version: 2.4
Name: patchmind
Version: 0.1.5
Summary: AI-powered Git patch assistant with HTML report generation.
Home-page: https://github.com/your-user/patchmind
Author: DOA
Classifier: Programming Language :: Python :: 3
Classifier: License :: OSI Approved :: MIT License
Classifier: Operating System :: OS Independent
Requires-Python: >=3.8
License-File: LICENSE
Requires-Dist: GitPython
Requires-Dist: jinja2
Requires-Dist: pyyaml
Requires-Dist: pytest
Requires-Dist: rich
Dynamic: author
Dynamic: classifier
Dynamic: description
Dynamic: description-content-type
Dynamic: home-page
Dynamic: license-file
Dynamic: requires-dist
Dynamic: requires-python
Dynamic: summary
